pymaginverse/__init__.py
pymaginverse/banded_tools/__init__.py
pymaginverse/banded_tools/build_banded.cp312-win_amd64.pyd
pymaginverse/banded_tools/build_banded.pyx
pymaginverse/banded_tools/utils.py
pymaginverse/damping_modules/__init__.py
pymaginverse/damping_modules/damp_types.py
pymaginverse/damping_modules/damping.py
pymaginverse/data_prep.py
pymaginverse/field_inversion.py
pymaginverse/forward_modules/__init__.py
pymaginverse/forward_modules/frechet.py
pymaginverse/forward_modules/fwtools.py
pymaginverse/tools/__init__.py
pymaginverse/tools/core.py
pymaginverse-1.2.0.dist-info/LICENSE
pymaginverse-1.2.0.dist-info/METADATA
pymaginverse-1.2.0.dist-info/WHEEL
pymaginverse-1.2.0.dist-info/RECORD
