Metadata-Version: 2.1
Name: pymaginverse
Version: 1.2.0
Summary: Python Library performing Geomagnetic Field inversions for (paleo)magnetic data
License: MIT
Author: Frenk Out
Author-email: outfrenk@gmail.com
Requires-Python: >=3.9,<3.13
Classifier: License :: OSI Approved :: MIT License
Classifier: Programming Language :: Python :: 3
Classifier: Programming Language :: Python :: 3.9
Classifier: Programming Language :: Python :: 3.10
Classifier: Programming Language :: Python :: 3.11
Classifier: Programming Language :: Python :: 3.12
Requires-Dist: Cartopy (>=0.18.0)
Requires-Dist: cython (>=3.0,<4.0)
Requires-Dist: matplotlib (>=3.8.3,<4.0.0)
Requires-Dist: numpy (>=1.26.4,<2.0.0)
Requires-Dist: pandas (>=2.2.1,<3.0.0)
Requires-Dist: pathlib (>=1.0.1,<2.0.0)
Requires-Dist: pyshtools (>=4.10.4,<5.0.0)
Requires-Dist: scipy (>=1.12.0,<2.0.0)
Requires-Dist: tqdm (>=4.66.1,<5.0.0)
